README.md
setup.py
ClockPaper/__init__.py
ClockPaper/clock.py
ClockPaper.egg-info/PKG-INFO
ClockPaper.egg-info/SOURCES.txt
ClockPaper.egg-info/dependency_links.txt
ClockPaper.egg-info/entry_points.txt
ClockPaper.egg-info/requires.txt
ClockPaper.egg-info/top_level.txt