Metadata-Version: 1.0
Name: ClockPaper
Version: 1.0
Summary: A python application in shell to show current time and date
Home-page: https://github.com/RayZhao1998/clockPy
Author: Ray Zhao
Author-email: rayzhao98@163.com
License: MIT
Platform: UNKNOWN
